melay/melay.srcs/sources_1/new/melay.v
`timescale 1ns/1ps

module melay(
input  in, rst,clk,
output out

);
//state assignment
parameter ST_zero = 1'b0;
parameter ST_one = 1'b1;
reg out;
//assign registers
reg state, next_state;
//logic of fsm
always @(posedge clk )  //state updatation
    
    if(rst)begin
       state <= ST_zero; 
    end
    else begin
        state <= next_state;
    end

always @( in, state)  //state computation and yput
  case (state)
    ST_zero:begin
        if(in)begin
            out <= 1'b1;
            next_state=ST_one;
            
        end
        else begin
            out <= 1'b0;
            next_state=state;
            end
    end
    ST_one: begin
        if(in)begin
            out <= 1'b1;
            next_state= state;
        end
        else begin
            out <= 1'b0;
            next_state = ST_zero;
        end
    end
endcase  




endmodule

tb_melay.v
`timescale 1ns/1ps

`include "melay.v"

module tb_melay();
reg in,rst;
wire out;
reg clk;
melay dut(in,rst,clk,out);

always begin
    clk<=0;
    #10;
    clk<=1;
    #10;
end

initial begin
    $dumpfile("melay.vcd");
    $dumpvars;
   
    rst <= 1;
    #20 rst<=0; 
    #20 in<=0;
    #20 in<=1;
    #20 in<=0;
    #20 in<=1;
    #20 in<=0;
    #20 $finish;
end

endmodule

melay.vcd
$date
	Thu Nov 16 12:14:41 2023
$end
$version
	Icarus Verilog
$end
$timescale
	1ps
$end
$scope module tb_melay $end
$var wire 1 ! out $end
$var reg 1 " clk $end
$var reg 1 # in $end
$var reg 1 $ rst $end
$scope module dut $end
$var wire 1 " clk $end
$var wire 1 # in $end
$var wire 1 $ rst $end
$var reg 1 % next_state $end
$var reg 1 ! out $end
$var reg 1 & state $end
$upscope $end
$upscope $end
$enddefinitions $end
#0
$dumpvars
x&
x%
1$
x#
0"
x!
$end
#10000
0!
0%
0&
1"
#20000
0"
0$
#30000
1"
#40000
0"
0#
#50000
1"
#60000
1!
1%
0"
1#
#70000
1&
1"
#80000
0!
0%
0"
0#
#90000
0&
1"
#100000
1!
1%
0"
1#
#110000
1&
1"
#120000
0!
0%
0"
0#
#130000
0&
1"
