payload.v
`timescale 1ns / 1ps

module PacketProcessor(
    input clock,
    input resetn,
    input [31:0] dataIn,
    input validIn,
    input lastIn,
    output reg [31:0] dataOut,
    output reg validOut,
    output reg lastOut
);

// Define the states
localparam IDLE = 0,
           COLLECT_DATA = 1,
           SEND_HEADER = 2,
           SEND_PAYLOAD = 3,
           SEND_FOOTER = 4;

// Internal Registers and Wires
reg [1:0] state, next_state;
reg [15:0] sequence_number;
reg [15:0] word_count;
reg [31:0] memory [0:380]; // Memory to store up to 381 words
reg [31:0] header;
integer i; // Loop variable for memory initialization

// Header and Footer
wire [31:0] footer = 32'hFFFFFFFF; // Static footer with all 1's

// State transition and output logic
always @(posedge clock or negedge resetn) begin
    if (!resetn) begin
        state <= IDLE;
        sequence_number <= 0;
        word_count <= 0;
        validOut <= 0;
        lastOut <= 0;
        // Initialize memory to zero
        for (i = 0; i < 381; i = i + 1) begin
            memory[i] <= 32'd0;
        end
    end else begin
        case (state)
            IDLE: begin
                if (validIn) begin
                    state <= COLLECT_DATA;
                    word_count <= 0;
                end
            end
            COLLECT_DATA: begin
                if (validIn) begin
                    // Store incoming data
                    memory[word_count] <= dataIn;
                    word_count <= word_count + 1;
                    if (lastIn) begin
                        // Prepare the header
                        header <= {sequence_number, word_count};
                        sequence_number <= sequence_number + 1;
                        state <= SEND_HEADER;
                    end
                end
            end
            SEND_HEADER: begin
                dataOut <= header;
                validOut <= 1;
                lastOut <= 0;
                state <= SEND_PAYLOAD;
                i <= 0; // Reset memory index
            end
            SEND_PAYLOAD: begin
                dataOut <= memory[i];
                validOut <= 1;
                lastOut <= 0;
                if (i >= word_count - 1) begin // Check if all words have been sent
                    state <= SEND_FOOTER;
                end else begin
                    i <= i + 1;
                end
            end
            SEND_FOOTER: begin
                dataOut <= footer;
                validOut <= 1;
                lastOut <= 1;
                state <= IDLE;
            end
            default: begin
                state <= IDLE;
            end
        endcase
    end
end

endmodule

tb_payload.v
`timescale 1ns / 1ps
`include "payload.v"
module PacketProcessor_tb;

// Parameters
localparam DATA_WIDTH = 32;
localparam MEMORY_DEPTH = 381;
localparam HEADER_WIDTH = 32;
localparam FOOTER_WIDTH = 32;

// Testbench Signals
reg tb_clock;
reg tb_resetn;
reg [DATA_WIDTH-1:0] tb_dataIn;
reg tb_validIn;
reg tb_lastIn;
wire [DATA_WIDTH-1:0] tb_dataOut;
wire tb_validOut;
wire tb_lastOut;

// Instance of PacketProcessor
PacketProcessor uut (
    .clock(tb_clock),
    .resetn(tb_resetn),
    .dataIn(tb_dataIn),
    .validIn(tb_validIn),
    .lastIn(tb_lastIn),
    .dataOut(tb_dataOut),
    .validOut(tb_validOut),
    .lastOut(tb_lastOut)
);

// Clock generation
initial begin
    tb_clock = 0;
    forever #5 tb_clock = ~tb_clock; // 100MHz Clock
end

// Test sequence
initial begin
    $dumpfile("payload.vcd");
    $dumpvars;

    // Initialize Inputs
    tb_resetn = 0;
    tb_dataIn = 0;
    tb_validIn = 0;
    tb_lastIn = 0;

    // Wait for global reset
    #100;
    tb_resetn = 1;

    // Send packets
    send_packet(10);
    send_packet(20);
    send_packet(MEMORY_DEPTH);

    // Finish testbench
    #100;
    $finish;
end

// Task to send a packet of specified length
task send_packet;
    input integer length;
    integer i;
    begin
        tb_validIn = 1;
        for (i = 0; i < length; i = i + 1) begin
            tb_dataIn = $random;
            tb_lastIn = (i == length - 1) ? 1'b1 : 1'b0;
            #10; // Wait for one clock cycle
        end
        tb_validIn = 0;
        tb_lastIn = 0;
        #20; // Wait before sending next packet
    end
endtask

// Monitor
initial begin
    $monitor("Time=%t, resetn=%b, dataIn=%h, validIn=%b, lastIn=%b, dataOut=%h, validOut=%b, lastOut=%b",
             $time, tb_resetn, tb_dataIn, tb_validIn, tb_lastIn, tb_dataOut, tb_validOut, tb_lastOut);
end

endmodule

payload.vcd
$date
	Tue Jan 16 21:40:44 2024
$end
$version
	Icarus Verilog
$end
$timescale
	1ps
$end
$scope module PacketProcessor_tb $end
$var wire 1 ! tb_validOut $end
$var wire 1 " tb_lastOut $end
$var wire 32 # tb_dataOut [31:0] $end
$var reg 1 $ tb_clock $end
$var reg 32 % tb_dataIn [31:0] $end
$var reg 1 & tb_lastIn $end
$var reg 1 ' tb_resetn $end
$var reg 1 ( tb_validIn $end
$scope module uut $end
$var wire 1 $ clock $end
$var wire 32 ) dataIn [31:0] $end
$var wire 32 * footer [31:0] $end
$var wire 1 & lastIn $end
$var wire 1 ' resetn $end
$var wire 1 ( validIn $end
$var reg 32 + dataOut [31:0] $end
$var reg 32 , header [31:0] $end
$var reg 1 " lastOut $end
$var reg 16 - sequence_number [15:0] $end
$var reg 2 . state [1:0] $end
$var reg 1 ! validOut $end
$var reg 16 / word_count [15:0] $end
$var integer 32 0 i [31:0] $end
$upscope $end
$scope task send_packet $end
$var integer 32 1 i [31:0] $end
$var integer 32 2 length [31:0] $end
$upscope $end
$upscope $end
$enddefinitions $end
#0
$dumpvars
bx 2
bx 1
b101111101 0
b0 /
b0 .
b0 -
bx ,
bx +
b11111111111111111111111111111111 *
b0 )
0(
0'
0&
b0 %
0$
bx #
0"
0!
$end
#5000
b101111101 0
1$
#10000
0$
#15000
b101111101 0
1$
#20000
0$
#25000
b101111101 0
1$
#30000
0$
#35000
b101111101 0
1$
#40000
0$
#45000
b101111101 0
1$
#50000
0$
#55000
b101111101 0
1$
#60000
0$
#65000
b101111101 0
1$
#70000
0$
#75000
b101111101 0
1$
#80000
0$
#85000
b101111101 0
1$
#90000
0$
#95000
b101111101 0
1$
#100000
0$
b10010000101010011010100100100 %
b10010000101010011010100100100 )
b0 1
1(
b1010 2
1'
#105000
b1 .
1$
#110000
0$
b11000000100010010101111010000001 %
b11000000100010010101111010000001 )
b1 1
#115000
b1 /
1$
#120000
0$
b10000100100001001101011000001001 %
b10000100100001001101011000001001 )
b10 1
#125000
b10 /
1$
#130000
0$
b10110001111100000101011001100011 %
b10110001111100000101011001100011 )
b11 1
#135000
b11 /
1$
#140000
0$
b110101110010111101100001101 %
b110101110010111101100001101 )
b100 1
#145000
b100 /
1$
#150000
0$
b1000110110111111001100110001101 %
b1000110110111111001100110001101 )
b101 1
#155000
b101 /
1$
#160000
0$
b10110010110000101000010001100101 %
b10110010110000101000010001100101 )
b110 1
#165000
b110 /
1$
#170000
0$
b10001001001101110101001000010010 %
b10001001001101110101001000010010 )
b111 1
#175000
b111 /
1$
#180000
0$
b111100111110001100000001 %
b111100111110001100000001 )
b1000 1
#185000
b1000 /
1$
#190000
0$
1&
b110110101111100110100001101 %
b110110101111100110100001101 )
b1001 1
#195000
b10 .
b1 -
b1000 ,
b1001 /
1$
#200000
0$
0&
0(
b1010 1
#205000
b0 0
b11 .
1!
b1000 #
b1000 +
1$
#210000
0$
#215000
b1 0
b11000000100010010101111010000001 #
b11000000100010010101111010000001 +
1$
#220000
0$
b111011001000111111000101110110 %
b111011001000111111000101110110 )
b0 1
1(
b10100 2
#225000
b10 0
b10000100100001001101011000001001 #
b10000100100001001101011000001001 +
1$
#230000
0$
b11110100011011100110100111101 %
b11110100011011100110100111101 )
b1 1
#235000
b11 0
b10110001111100000101011001100011 #
b10110001111100000101011001100011 +
1$
#240000
0$
b1110110110101000101011111101101 %
b1110110110101000101011111101101 )
b10 1
#245000
b100 0
b110101110010111101100001101 #
b110101110010111101100001101 +
1$
#250000
0$
b1000110001011011111011110001100 %
b1000110001011011111011110001100 )
b11 1
#255000
b101 0
b1000110110111111001100110001101 #
b1000110110111111001100110001101 +
1$
#260000
0$
b1111100111111011110100111111001 %
b1111100111111011110100111111001 )
b100 1
#265000
b110 0
b10110010110000101000010001100101 #
b10110010110000101000010001100101 +
1$
#270000
0$
b11100011001101110010010011000110 %
b11100011001101110010010011000110 )
b101 1
#275000
b111 0
b10001001001101110101001000010010 #
b10001001001101110101001000010010 +
1$
#280000
0$
b11100010111101111000010011000101 %
b11100010111101111000010011000101 )
b110 1
#285000
b1000 0
b111100111110001100000001 #
b111100111110001100000001 +
1$
#290000
0$
b11010101000100111101001010101010 %
b11010101000100111101001010101010 )
b111 1
#295000
b0 .
b110110101111100110100001101 #
b110110101111100110100001101 +
1$
#300000
0$
b1110010101011111111011111100101 %
b1110010101011111111011111100101 )
b1000 1
#305000
b0 /
b1 .
1$
#310000
0$
b10111011110100100111001001110111 %
b10111011110100100111001001110111 )
b1001 1
#315000
b1 /
1$
#320000
0$
b10001001001100101101011000010010 %
b10001001001100101101011000010010 )
b1010 1
#325000
b10 /
1$
#330000
0$
b1000111111011001101101110001111 %
b1000111111011001101101110001111 )
b1011 1
#335000
b11 /
1$
#340000
0$
b1111001001100000110100111110010 %
b1111001001100000110100111110010 )
b1100 1
#345000
b100 /
1$
#350000
0$
b11100111011101101001011011001110 %
b11100111011101101001011011001110 )
b1101 1
#355000
b101 /
1$
#360000
0$
b11110100000000000111101011101000 %
b11110100000000000111101011101000 )
b1110 1
#365000
b110 /
1$
#370000
0$
b11100010110010100100111011000101 %
b11100010110010100100111011000101 )
b1111 1
#375000
b111 /
1$
#380000
0$
b101110010110000100100101011100 %
b101110010110000100100101011100 )
b10000 1
#385000
b1000 /
1$
#390000
0$
b11011110100011100010100010111101 %
b11011110100011100010100010111101 )
b10001 1
#395000
b1001 /
1$
#400000
0$
b10010110101010110101100000101101 %
b10010110101010110101100000101101 )
b10010 1
#405000
b1010 /
1$
#410000
0$
1&
b10110010101001110010011001100101 %
b10110010101001110010011001100101 )
b10011 1
#415000
b10 .
b10 -
b10000000000001010 ,
b1011 /
1$
#420000
0$
0&
0(
b10100 1
#425000
b0 0
b11 .
b10000000000001010 #
b10000000000001010 +
1$
#430000
0$
#435000
b1 0
b10111011110100100111001001110111 #
b10111011110100100111001001110111 +
1$
#440000
0$
b10110001111011110110001001100011 %
b10110001111011110110001001100011 )
b0 1
1(
b101111101 2
#445000
b10 0
b10001001001100101101011000010010 #
b10001001001100101101011000010010 +
1$
#450000
0$
b101011100111000011100001010 %
b101011100111000011100001010 )
b1 1
#455000
b11 0
b1000111111011001101101110001111 #
b1000111111011001101101110001111 +
1$
#460000
0$
b11000000001110110010001010000000 %
b11000000001110110010001010000000 )
b10 1
#465000
b100 0
b1111001001100000110100111110010 #
b1111001001100000110100111110010 +
1$
#470000
0$
b10000011001000010000100100000 %
b10000011001000010000100100000 )
b11 1
#475000
b101 0
b11100111011101101001011011001110 #
b11100111011101101001011011001110 +
1$
#480000
0$
b1010101011110000100010110101010 %
b1010101011110000100010110101010 )
b100 1
#485000
b110 0
b11110100000000000111101011101000 #
b11110100000000000111101011101000 +
1$
#490000
0$
b11001110110011001100110010011101 %
b11001110110011001100110010011101 )
b101 1
#495000
b111 0
b11100010110010100100111011000101 #
b11100010110010100100111011000101 +
1$
#500000
0$
b11001011001000000011111010010110 %
b11001011001000000011111010010110 )
b110 1
#505000
b1000 0
b101110010110000100100101011100 #
b101110010110000100100101011100 +
1$
#510000
0$
b10001001100000111011100000010011 %
b10001001100000111011100000010011 )
b111 1
#515000
b1001 0
b11011110100011100010100010111101 #
b11011110100011100010100010111101 +
1$
#520000
0$
b10000110101111000011100000001101 %
b10000110101111000011100000001101 )
b1000 1
#525000
b1010 0
b10010110101010110101100000101101 #
b10010110101010110101100000101101 +
1$
#530000
0$
b10101001101001111101011001010011 %
b10101001101001111101011001010011 )
b1001 1
#535000
b0 .
b10110010101001110010011001100101 #
b10110010101001110010011001100101 +
1$
#540000
0$
b110101100111111101110101101011 %
b110101100111111101110101101011 )
b1010 1
#545000
b0 /
b1 .
1$
#550000
0$
b11101010101001100010101011010101 %
b11101010101001100010101011010101 )
b1011 1
#555000
b1 /
1$
#560000
0$
b10000001000101110100101000000010 %
b10000001000101110100101000000010 )
b1100 1
#565000
b10 /
1$
#570000
0$
b11010111010101100011111010101110 %
b11010111010101100011111010101110 )
b1101 1
#575000
b11 /
1$
#580000
0$
b1110111111111110100100011101 %
b1110111111111110100100011101 )
b1110 1
#585000
b100 /
1$
#590000
0$
b11100111110001010111001011001111 %
b11100111110001010111001011001111 )
b1111 1
#595000
b101 /
1$
#600000
0$
b10001100001000100100100100011 %
b10001100001000100100100100011 )
b10000 1
#605000
b110 /
1$
#610000
0$
b101000010010110010100001010 %
b101000010010110010100001010 )
b10001 1
#615000
b111 /
1$
#620000
0$
b11100101011100110000101011001010 %
b11100101011100110000101011001010 )
b10010 1
#625000
b1000 /
1$
#630000
0$
b10011110001100010100110000111100 %
b10011110001100010100110000111100 )
b10011 1
#635000
b1001 /
1$
#640000
0$
b1111001011010001011110111110010 %
b1111001011010001011110111110010 )
b10100 1
#645000
b1010 /
1$
#650000
0$
b1000101001011100110000110001010 %
b1000101001011100110000110001010 )
b10101 1
#655000
b1011 /
1$
#660000
0$
b100000110001001011001101000001 %
b100000110001001011001101000001 )
b10110 1
#665000
b1100 /
1$
#670000
0$
b11101100010010110011010011011000 %
b11101100010010110011010011011000 )
b10111 1
#675000
b1101 /
1$
#680000
0$
b111100001000001111001101111000 %
b111100001000001111001101111000 )
b11000 1
#685000
b1110 /
1$
#690000
0$
b11000100100010100001001010001001 %
b11000100100010100001001010001001 )
b11001 1
#695000
b1111 /
1$
#700000
0$
b1110101110001010000110111101011 %
b1110101110001010000110111101011 )
b11010 1
#705000
b10000 /
1$
#710000
0$
b1011011000000100110010110110110 %
b1011011000000100110010110110110 )
b11011 1
#715000
b10001 /
1$
#720000
0$
b1100011010010111111100111000110 %
b1100011010010111111100111000110 )
b11100 1
#725000
b10010 /
1$
#730000
0$
b1010111000101010001001110101110 %
b1010111000101010001001110101110 )
b11101 1
#735000
b10011 /
1$
#740000
0$
b11011110011101010000001010111100 %
b11011110011101010000001010111100 )
b11110 1
#745000
b10100 /
1$
#750000
0$
b10101000011111101110100101010 %
b10101000011111101110100101010 )
b11111 1
#755000
b10101 /
1$
#760000
0$
b10000101110101111001101000001011 %
b10000101110101111001101000001011 )
b100000 1
#765000
b10110 /
1$
#770000
0$
b10111000100101111011111001110001 %
b10111000100101111011111001110001 )
b100001 1
#775000
b10111 /
1$
#780000
0$
b1000010111100100100000110000101 %
b1000010111100100100000110000101 )
b100010 1
#785000
b11000 /
1$
#790000
0$
b100111111100100101010101001111 %
b100111111100100101010101001111 )
b100011 1
#795000
b11001 /
1$
#800000
0$
b10011101110011000110000000111011 %
b10011101110011000110000000111011 )
b100100 1
#805000
b11010 /
1$
#810000
0$
b11101000001100011001100111010 %
b11101000001100011001100111010 )
b100101 1
#815000
b11011 /
1$
#820000
0$
b10111111001000110011001001111110 %
b10111111001000110011001001111110 )
b100110 1
#825000
b11100 /
1$
#830000
0$
b1010101010100100101100010101 %
b1010101010100100101100010101 )
b100111 1
#835000
b11101 /
1$
#840000
0$
b1111000110110011001101111110001 %
b1111000110110011001101111110001 )
b101000 1
#845000
b11110 /
1$
#850000
0$
b1101100100111000100101111011001 %
b1101100100111000100101111011001 )
b101001 1
#855000
b11111 /
1$
#860000
0$
b110001001000110000011101100010 %
b110001001000110000011101100010 )
b101010 1
#865000
b100000 /
1$
#870000
0$
b100110001101011111101101001100 %
b100110001101011111101101001100 )
b101011 1
#875000
b100001 /
1$
#880000
0$
b1001111101000010101010110011111 %
b1001111101000010101010110011111 )
b101100 1
#885000
b100010 /
1$
#890000
0$
b1000111101110011010000110001111 %
b1000111101110011010000110001111 )
b101101 1
#895000
b100011 /
1$
#900000
0$
b1111100011011011010100111111000 %
b1111100011011011010100111111000 )
b101110 1
#905000
b100100 /
1$
#910000
0$
b11011011110011010110000010110111 %
b11011011110011010110000010110111 )
b101111 1
#915000
b100101 /
1$
#920000
0$
b11001111110001000101011010011111 %
b11001111110001000101011010011111 )
b110000 1
#925000
b100110 /
1$
#930000
0$
b10101110011111011001010001011100 %
b10101110011111011001010001011100 )
b110001 1
#935000
b100111 /
1$
#940000
0$
b10101101110010111100000001011011 %
b10101101110010111100000001011011 )
b110010 1
#945000
b101000 /
1$
#950000
0$
b1000100110111100011011110001001 %
b1000100110111100011011110001001 )
b110011 1
#955000
b101001 /
1$
#960000
0$
b10100100101011100011001001001001 %
b10100100101011100011001001001001 )
b110100 1
#965000
b101010 /
1$
#970000
0$
b11101000001000110011111011010000 %
b11101000001000110011111011010000 )
b110101 1
#975000
b101011 /
1$
#980000
0$
b11101011111111101100000011010111 %
b11101011111111101100000011010111 )
b110110 1
#985000
b101100 /
1$
#990000
0$
b10101000110001111111110001010001 %
b10101000110001111111110001010001 )
b110111 1
#995000
b101101 /
1$
#1000000
0$
b1001011001000010010111110010110 %
b1001011001000010010111110010110 )
b111000 1
#1005000
b101110 /
1$
#1010000
0$
b110000111010111111100001100 %
b110000111010111111100001100 )
b111001 1
#1015000
b101111 /
1$
#1020000
0$
b11100001001011001100111011000010 %
b11100001001011001100111011000010 )
b111010 1
#1025000
b110000 /
1$
#1030000
0$
b1100100010101111110110111001000 %
b1100100010101111110110111001000 )
b111011 1
#1035000
b110001 /
1$
#1040000
0$
b10111011100000100101101001110111 %
b10111011100000100101101001110111 )
b111100 1
#1045000
b110010 /
1$
#1050000
0$
b11110111100101110110100111101 %
b11110111100101110110100111101 )
b111101 1
#1055000
b110011 /
1$
#1060000
0$
b1001000011001101101100010010 %
b1001000011001101101100010010 )
b111110 1
#1065000
b110100 /
1$
#1070000
0$
b10111111000001010000000001111110 %
b10111111000001010000000001111110 )
b111111 1
#1075000
b110101 /
1$
#1080000
0$
b110110111001011000000101101101 %
b110110111001011000000101101101 )
b1000000 1
#1085000
b110110 /
1$
#1090000
0$
b11100110110011110011100111001 %
b11100110110011110011100111001 )
b1000001 1
#1095000
b110111 /
1$
#1100000
0$
b1111110100101000111100011111 %
b1111110100101000111100011111 )
b1000010 1
#1105000
b111000 /
1$
#1110000
0$
b11101001111010111111011011010011 %
b11101001111010111111011011010011 )
b1000011 1
#1115000
b111001 /
1$
#1120000
0$
b1000010110110010010111110000101 %
b1000010110110010010111110000101 )
b1000100 1
#1125000
b111010 /
1$
#1130000
0$
b10111100000101001000100001111000 %
b10111100000101001000100001111000 )
b1000101 1
#1135000
b111011 /
1$
#1140000
0$
b101101110110100101100101011011 %
b101101110110100101100101011011 )
b1000110 1
#1145000
b111100 /
1$
#1150000
0$
b100100100010110100101101001001 %
b100100100010110100101101001001 )
b1000111 1
#1155000
b111101 /
1$
#1160000
0$
b10011111111100101010111000111111 %
b10011111111100101010111000111111 )
b1001000 1
#1165000
b111110 /
1$
#1170000
0$
b10101000011001010111100101010 %
b10101000011001010111100101010 )
b1001001 1
#1175000
b111111 /
1$
#1180000
0$
b101100000101010110001101011000 %
b101100000101010110001101011000 )
b1001010 1
#1185000
b1000000 /
1$
#1190000
0$
b11000011001111110011100010000110 %
b11000011001111110011100010000110 )
b1001011 1
#1195000
b1000001 /
1$
#1200000
0$
b11000111000110100000110010001110 %
b11000111000110100000110010001110 )
b1001100 1
#1205000
b1000010 /
1$
#1210000
0$
b11001110001011111111001010011100 %
b11001110001011111111001010011100 )
b1001101 1
#1215000
b1000011 /
1$
#1220000
0$
b1111101001101011001100111111010 %
b1111101001101011001100111111010 )
b1001110 1
#1225000
b1000100 /
1$
#1230000
0$
b10010011011111011011110000100110 %
b10010011011111011011110000100110 )
b1001111 1
#1235000
b1000101 /
1$
#1240000
0$
b111001100101100001011101110011 %
b111001100101100001011101110011 )
b1010000 1
#1245000
b1000110 /
1$
#1250000
0$
b11010001100010111011010010100011 %
b11010001100010111011010010100011 )
b1010001 1
#1255000
b1000111 /
1$
#1260000
0$
b10010111100110011010100000101111 %
b10010111100110011010100000101111 )
b1010010 1
#1265000
b1001000 /
1$
#1270000
0$
b11011001110100101001001010110011 %
b11011001110100101001001010110011 )
b1010011 1
#1275000
b1001001 /
1$
#1280000
0$
b10101111110110000101011001011111 %
b10101111110110000101011001011111 )
b1010100 1
#1285000
b1001010 /
1$
#1290000
0$
b100010001010010000110101000100 %
b100010001010010000110101000100 )
b1010101 1
#1295000
b1001011 /
1$
#1300000
0$
b1111011111110001111110111110111 %
b1111011111110001111110111110111 )
b1010110 1
#1305000
b1001100 /
1$
#1310000
0$
b11100101100110110011011011001011 %
b11100101100110110011011011001011 )
b1010111 1
#1315000
b1001101 /
1$
#1320000
0$
b11110011000010010001101011100110 %
b11110011000010010001101011100110 )
b1011000 1
#1325000
b1001110 /
1$
#1330000
0$
b101101001010001101101101011010 %
b101101001010001101101101011010 )
b1011001 1
#1335000
b1001111 /
1$
#1340000
0$
b10100110011111100000100101001 %
b10100110011111100000100101001 )
b1011010 1
#1345000
b1010000 /
1$
#1350000
0$
b11110110100000101110001011101101 %
b11110110100000101110001011101101 )
b1011011 1
#1355000
b1010001 /
1$
#1360000
0$
b11101101010100110110110011011010 %
b11101101010100110110110011011010 )
b1011100 1
#1365000
b1010010 /
1$
#1370000
0$
b10110010100111111011011001100101 %
b10110010100111111011011001100101 )
b1011101 1
#1375000
b1010011 /
1$
#1380000
0$
b11011010100010101110001010110101 %
b11011010100010101110001010110101 )
b1011110 1
#1385000
b1010100 /
1$
#1390000
0$
b11101111101111101001010011011111 %
b11101111101111101001010011011111 )
b1011111 1
#1395000
b1010101 /
1$
#1400000
0$
b111100111100010001100101111001 %
b111100111100010001100101111001 )
b1100000 1
#1405000
b1010110 /
1$
#1410000
0$
b100010001100011111111101000100 %
b100010001100011111111101000100 )
b1100001 1
#1415000
b1010111 /
1$
#1420000
0$
b11101000011101000000110011010000 %
b11101000011101000000110011010000 )
b1100010 1
#1425000
b1011000 /
1$
#1430000
0$
b10101000010010000101100101010 %
b10101000010010000101100101010 )
b1100011 1
#1435000
b1011001 /
1$
#1440000
0$
b1010101111101101010110110101011 %
b1010101111101101010110110101011 )
b1100100 1
#1445000
b1011010 /
1$
#1450000
0$
b111011011111100111100001110 %
b111011011111100111100001110 )
b1100101 1
#1455000
b1011011 /
1$
#1460000
0$
b1101110010111011010110111011100 %
b1101110010111011010110111011100 )
b1100110 1
#1465000
b1011100 /
1$
#1470000
0$
b11001101010111101011110010011010 %
b11001101010111101011110010011010 )
b1100111 1
#1475000
b1011101 /
1$
#1480000
0$
b11111110110111110111001011111101 %
b11111110110111110111001011111101 )
b1101000 1
#1485000
b1011110 /
1$
#1490000
0$
b11100001111100010000001011000011 %
b11100001111100010000001011000011 )
b1101001 1
#1495000
b1011111 /
1$
#1500000
0$
b101011000011101110110101010110 %
b101011000011101110110101010110 )
b1101010 1
#1505000
b1100000 /
1$
#1510000
0$
b100111011110011110100101001110 %
b100111011110011110100101001110 )
b1101011 1
#1515000
b1100001 /
1$
#1520000
0$
b10110011110110010111011001100111 %
b10110011110110010111011001100111 )
b1101100 1
#1525000
b1100010 /
1$
#1530000
0$
b10000101001100010011010000001010 %
b10000101001100010011010000001010 )
b1101101 1
#1535000
b1100011 /
1$
#1540000
0$
b1011011011011111011100110110110 %
b1011011011011111011100110110110 )
b1101110 1
#1545000
b1100100 /
1$
#1550000
0$
b10011100000011101000101000111000 %
b10011100000011101000101000111000 )
b1101111 1
#1555000
b1100101 /
1$
#1560000
0$
b111100110100011000011101111001 %
b111100110100011000011101111001 )
b1110000 1
#1565000
b1100110 /
1$
#1570000
0$
b11011100001010111100010010111000 %
b11011100001010111100010010111000 )
b1110001 1
#1575000
b1100111 /
1$
#1580000
0$
b1001010011101001011111110010100 %
b1001010011101001011111110010100 )
b1110010 1
#1585000
b1101000 /
1$
#1590000
0$
b1001001110001100101110110010011 %
b1001001110001100101110110010011 )
b1110011 1
#1595000
b1101001 /
1$
#1600000
0$
b10000010001111110010110000000100 %
b10000010001111110010110000000100 )
b1110100 1
#1605000
b1101010 /
1$
#1610000
0$
b10101100101101111100101001011001 %
b10101100101101111100101001011001 )
b1110101 1
#1615000
b1101011 /
1$
#1620000
0$
b1101101110010110110100111011011 %
b1101101110010110110100111011011 )
b1110110 1
#1625000
b1101100 /
1$
#1630000
0$
b10100110111111001101111001001101 %
b10100110111111001101111001001101 )
b1110111 1
#1635000
b1101101 /
1$
#1640000
0$
b1101100101100001011011111011001 %
b1101100101100001011011111011001 )
b1111000 1
#1645000
b1101110 /
1$
#1650000
0$
b10110110101001000010011001101101 %
b10110110101001000010011001101101 )
b1111001 1
#1655000
b1101111 /
1$
#1660000
0$
b10111011010001011110001001110110 %
b10111011010001011110001001110110 )
b1111010 1
#1665000
b1110000 /
1$
#1670000
0$
b1100101001110110100100111001010 %
b1100101001110110100100111001010 )
b1111011 1
#1675000
b1110001 /
1$
#1680000
0$
b1011011000101110010110110110110 %
b1011011000101110010110110110110 )
b1111100 1
#1685000
b1110010 /
1$
#1690000
0$
b1001010100100110111000110010101 %
b1001010100100110111000110010101 )
b1111101 1
#1695000
b1110011 /
1$
#1700000
0$
b10100011000001110001101001000110 %
b10100011000001110001101001000110 )
b1111110 1
#1705000
b1110100 /
1$
#1710000
0$
b10011101001001101100000100 %
b10011101001001101100000100 )
b1111111 1
#1715000
b1110101 /
1$
#1720000
0$
b1111011110100100110000111110111 %
b1111011110100100110000111110111 )
b10000000 1
#1725000
b1110110 /
1$
#1730000
0$
b110100100110000000011101101001 %
b110100100110000000011101101001 )
b10000001 1
#1735000
b1110111 /
1$
#1740000
0$
b11011010011011101011101010110100 %
b11011010011011101011101010110100 )
b10000010 1
#1745000
b1111000 /
1$
#1750000
0$
b1000100000000011000110110001000 %
b1000100000000011000110110001000 )
b10000011 1
#1755000
b1111001 /
1$
#1760000
0$
b10100011111001101100100101000 %
b10100011111001101100100101000 )
b10000100 1
#1765000
b1111010 /
1$
#1770000
0$
b10010110100100000000010000101101 %
b10010110100100000000010000101101 )
b10000101 1
#1775000
b1111011 /
1$
#1780000
0$
b11100011110001010011000011000111 %
b11100011110001010011000011000111 )
b10000110 1
#1785000
b1111100 /
1$
#1790000
0$
b10010111010111001001110000101110 %
b10010111010111001001110000101110 )
b10000111 1
#1795000
b1111101 /
1$
#1800000
0$
b10000100011101111110010000001000 %
b10000100011101111110010000001000 )
b10001000 1
#1805000
b1111110 /
1$
#1810000
0$
b1110010000010100010100011100 %
b1110010000010100010100011100 )
b10001001 1
#1815000
b1111111 /
1$
#1820000
0$
b11111110101001111010011011111101 %
b11111110101001111010011011111101 )
b10001010 1
#1825000
b10000000 /
1$
#1830000
0$
b10100100111100000011100101001 %
b10100100111100000011100101001 )
b10001011 1
#1835000
b10000001 /
1$
#1840000
0$
b10001110001101111001000000011100 %
b10001110001101111001000000011100 )
b10001100 1
#1845000
b10000010 /
1$
#1850000
0$
b1000011001101010110011110000110 %
b1000011001101010110011110000110 )
b10001101 1
#1855000
b10000011 /
1$
#1860000
0$
b11101101001101000000100011011010 %
b11101101001101000000100011011010 )
b10001110 1
#1865000
b10000100 /
1$
#1870000
0$
b10011110101101111100011000111101 %
b10011110101101111100011000111101 )
b10001111 1
#1875000
b10000101 /
1$
#1880000
0$
b110011010011101010011101100110 %
b110011010011101010011101100110 )
b10010000 1
#1885000
b10000110 /
1$
#1890000
0$
b10111000010101011100010001110000 %
b10111000010101011100010001110000 )
b10010001 1
#1895000
b10000111 /
1$
#1900000
0$
b10111001111101010000010001110011 %
b10111001111101010000010001110011 )
b10010010 1
#1905000
b10001000 /
1$
#1910000
0$
b1011101011100011001100110111010 %
b1011101011100011001100110111010 )
b10010011 1
#1915000
b10001001 /
1$
#1920000
0$
b101111001110101011001101011110 %
b101111001110101011001101011110 )
b10010100 1
#1925000
b10001010 /
1$
#1930000
0$
b1111101010001110111100111111010 %
b1111101010001110111100111111010 )
b10010101 1
#1935000
b10001011 /
1$
#1940000
0$
b1101010100011100000010111010101 %
b1101010100011100000010111010101 )
b10010110 1
#1945000
b10001100 /
1$
#1950000
0$
b10001101001001001111011000011010 %
b10001101001001001111011000011010 )
b10010111 1
#1955000
b10001101 /
1$
#1960000
0$
b11011100111100000000000010111001 %
b11011100111100000000000010111001 )
b10011000 1
#1965000
b10001110 /
1$
#1970000
0$
b11011100001110110000100110111 %
b11011100001110110000100110111 )
b10011001 1
#1975000
b10001111 /
1$
#1980000
0$
b1001011001001110011011110010110 %
b1001011001001110011011110010110 )
b10011010 1
#1985000
b10010000 /
1$
#1990000
0$
b1100000001110010010000111000000 %
b1100000001110010010000111000000 )
b10011011 1
#1995000
b10010001 /
1$
#2000000
0$
b10011001001011001111100100110 %
b10011001001011001111100100110 )
b10011100 1
#2005000
b10010010 /
1$
#2010000
0$
b11011011010001100001101010110110 %
b11011011010001100001101010110110 )
b10011101 1
#2015000
b10010011 /
1$
#2020000
0$
b111110100110011000001101111101 %
b111110100110011000001101111101 )
b10011110 1
#2025000
b10010100 /
1$
#2030000
0$
b1101110010111110000111111011100 %
b1101110010111110000111111011100 )
b10011111 1
#2035000
b10010101 /
1$
#2040000
0$
b1000011011000010101011110000110 %
b1000011011000010101011110000110 )
b10100000 1
#2045000
b10010110 /
1$
#2050000
0$
b111100000000111111111101111000 %
b111100000000111111111101111000 )
b10100001 1
#2055000
b10010111 /
1$
#2060000
0$
b111111010110101001101101111110 %
b111111010110101001101101111110 )
b10100010 1
#2065000
b10011000 /
1$
#2070000
0$
b11101101100011011000000011011011 %
b11101101100011011000000011011011 )
b10100011 1
#2075000
b10011001 /
1$
#2080000
0$
b11100111110000111011011011001111 %
b11100111110000111011011011001111 )
b10100100 1
#2085000
b10011010 /
1$
#2090000
0$
b111100111011010010101101111001 %
b111100111011010010101101111001 )
b10100101 1
#2095000
b10011011 /
1$
#2100000
0$
b11111101001010001110010011111010 %
b11111101001010001110010011111010 )
b10100110 1
#2105000
b10011100 /
1$
#2110000
0$
b10110000101111001110111001100001 %
b10110000101111001110111001100001 )
b10100111 1
#2115000
b10011101 /
1$
#2120000
0$
b1011100101000000100100010111 %
b1011100101000000100100010111 )
b10101000 1
#2125000
b10011110 /
1$
