payload.v
`timescale 1ns / 1ps

module PacketProcessor(
    input clock,
    input resetn,
    input [31:0] dataIn,
    input validIn,
    input lastIn,
    output reg [31:0] dataOut,
    output reg validOut,
    output reg lastOut
);

// Define the states
localparam IDLE = 0,
           COLLECT_DATA = 1,
           SEND_HEADER = 2,
           SEND_PAYLOAD = 3,
           SEND_FOOTER = 4;

// Internal Registers and Wires
reg [1:0] state, next_state;
reg [15:0] sequence_number;
reg [15:0] word_count;
reg [31:0] memory [0:380]; // Memory to store up to 381 words
reg [31:0] header;
integer i; // Loop variable for memory initialization

// Header and Footer
wire [31:0] footer = 32'hFFFFFFFF; // Static footer with all 1's

// State transition and output logic
always @(posedge clock or negedge resetn) begin
    if (!resetn) begin
        state <= IDLE;
        sequence_number <= 0;
        word_count <= 0;
        validOut <= 0;
        lastOut <= 0;
        // Initialize memory to zero
        for (i = 0; i < 381; i = i + 1) begin
            memory[i] <= 32'd0;
        end
    end else begin
        case (state)
            IDLE: begin
                if (validIn) begin
                    state <= COLLECT_DATA;
                    word_count <= 0;
                end
            end
            COLLECT_DATA: begin
                if (validIn) begin
                    // Store incoming data
                    memory[word_count] <= dataIn;
                    word_count <= word_count + 1;
                    if (lastIn) begin
                        // Prepare the header
                        header <= {sequence_number, word_count};
                        sequence_number <= sequence_number + 1;
                        state <= SEND_HEADER;
                    end
                end
            end
            SEND_HEADER: begin
                dataOut <= header;
                validOut <= 1;
                lastOut <= 0;
                state <= SEND_PAYLOAD;
                i <= 0; // Reset memory index
            end
            SEND_PAYLOAD: begin
                dataOut <= memory[i];
                validOut <= 1;
                lastOut <= 0;
                if (i >= word_count - 1) begin // Check if all words have been sent
                    state <= SEND_FOOTER;
                end else begin
                    i <= i + 1;
                end
            end
            SEND_FOOTER: begin
                dataOut <= footer;
                validOut <= 1;
                lastOut <= 1;
                state <= IDLE;
            end
            default: begin
                state <= IDLE;
            end
        endcase
    end
end

endmodule

tb_payload.v
`timescale 1ns / 1ps
`include "payload.v"
module PacketProcessor_tb;

// Parameters
localparam DATA_WIDTH = 32;
localparam MEMORY_DEPTH = 381;
localparam HEADER_WIDTH = 32;
localparam FOOTER_WIDTH = 32;

// Testbench Signals
reg tb_clock;
reg tb_resetn;
reg [DATA_WIDTH-1:0] tb_dataIn;
reg tb_validIn;
reg tb_lastIn;
wire [DATA_WIDTH-1:0] tb_dataOut;
wire tb_validOut;
wire tb_lastOut;

// Instance of PacketProcessor
PacketProcessor uut (
    .clock(tb_clock),
    .resetn(tb_resetn),
    .dataIn(tb_dataIn),
    .validIn(tb_validIn),
    .lastIn(tb_lastIn),
    .dataOut(tb_dataOut),
    .validOut(tb_validOut),
    .lastOut(tb_lastOut)
);

// Clock generation
initial begin
    tb_clock = 0;
    forever #5 tb_clock = ~tb_clock; // 100MHz Clock
end

// Test sequence
initial begin
    $dumpfile("payload.vcd");
    $dumpvars;

    // Initialize Inputs
    tb_resetn = 0;
    tb_dataIn = 0;
    tb_validIn = 0;
    tb_lastIn = 0;

    // Wait for global reset
    #100;
    tb_resetn = 1;

    // Send packets
    send_packet(10);
    send_packet(20);
    send_packet(MEMORY_DEPTH);

    // Finish testbench
    #100;
    $finish;
end

// Task to send a packet of specified length
task send_packet;
    input integer length;
    integer i;
    begin
        tb_validIn = 1;
        for (i = 0; i < length; i = i + 1) begin
            tb_dataIn = $random;
            tb_lastIn = (i == length - 1) ? 1'b1 : 1'b0;
            #10; // Wait for one clock cycle
        end
        tb_validIn = 0;
        tb_lastIn = 0;
        #20; // Wait before sending next packet
    end
endtask

// Monitor
initial begin
    $monitor("Time=%t, resetn=%b, dataIn=%h, validIn=%b, lastIn=%b, dataOut=%h, validOut=%b, lastOut=%b",
             $time, tb_resetn, tb_dataIn, tb_validIn, tb_lastIn, tb_dataOut, tb_validOut, tb_lastOut);
end

endmodule

processor_payload/processor_payload.sim/sim_1/behav/xsim/payload.vcd
$date
   Tue Jan 16 22:02:29 2024
$end
$version
  2023.1
$end
$timescale
  1ps
$end
$scope module PacketProcessor_tb $end
$var reg 1 ! tb_clock $end
$var reg 1 " tb_resetn $end
$var reg 32 # tb_dataIn [31:0] $end
$var reg 1 $ tb_validIn $end
$var reg 1 % tb_lastIn $end
$var wire 32 & tb_dataOut [31:0] $end
$var wire 1 ' tb_validOut $end
$var wire 1 ( tb_lastOut $end
$scope module uut $end
$var wire 1 ) clock $end
$var wire 1 * resetn $end
$var wire 32 + dataIn [31:0] $end
$var wire 1 , validIn $end
$var wire 1 - lastIn $end
$var reg 32 . dataOut [31:0] $end
$var reg 1 / validOut $end
$var reg 1 0 lastOut $end
$var reg 2 1 state [1:0] $end
$var reg 2 2 next_state [1:0] $end
$var reg 16 3 sequence_number [15:0] $end
$var reg 16 4 word_count [15:0] $end
$var reg 32 5 header [31:0] $end
$var integer 32 6 i [31:0] $end
$var wire 32 7 footer [31:0] $end
$upscope $end
$scope task send_packet $end
$var integer 32 8 length [31:0] $end
$var integer 32 9 i [31:0] $end
$upscope $end
$upscope $end
$enddefinitions $end
#0
$dumpvars
0!
0"
b0 #
0$
0%
bx &
0'
0(
0)
0*
b0 +
0,
0-
bx .
0/
00
b0 1
bx 2
b0 3
b0 4
bx 5
bx 6
b11111111111111111111111111111111 7
bx 8
bx 9
$end
#5000
1!
1)
#10000
0!
0)
#15000
1!
1)
#20000
0!
0)
#25000
1!
1)
#30000
0!
0)
#35000
1!
1)
#40000
0!
0)
#45000
1!
1)
#50000
0!
0)
#55000
1!
1)
#60000
0!
0)
#65000
1!
1)
#70000
0!
0)
#75000
1!
1)
#80000
0!
0)
#85000
1!
1)
#90000
0!
0)
#95000
1!
1)
#100000
0!
1"
b10010000101010011010100100100 #
1$
0)
1*
b10010000101010011010100100100 +
1,
b1010 8
b0 9
#105000
1!
1)
b1 1
#110000
0!
b11000000100010010101111010000001 #
0)
b11000000100010010101111010000001 +
b1 9
#115000
1!
1)
b1 4
#120000
0!
b10000100100001001101011000001001 #
0)
b10000100100001001101011000001001 +
b10 9
#125000
1!
1)
b10 4
#130000
0!
b10110001111100000101011001100011 #
0)
b10110001111100000101011001100011 +
b11 9
#135000
1!
1)
b11 4
#140000
0!
b110101110010111101100001101 #
0)
b110101110010111101100001101 +
b100 9
#145000
1!
1)
b100 4
#150000
0!
b1000110110111111001100110001101 #
0)
b1000110110111111001100110001101 +
b101 9
#155000
1!
1)
b101 4
#160000
0!
b10110010110000101000010001100101 #
0)
b10110010110000101000010001100101 +
b110 9
#165000
1!
1)
b110 4
#170000
0!
b10001001001101110101001000010010 #
0)
b10001001001101110101001000010010 +
b111 9
#175000
1!
1)
b111 4
#180000
0!
b111100111110001100000001 #
0)
b111100111110001100000001 +
b1000 9
#185000
1!
1)
b1000 4
#190000
0!
b110110101111100110100001101 #
1%
0)
b110110101111100110100001101 +
1-
b1001 9
#195000
1!
1)
b10 1
b1 3
b1001 4
b1000 5
#200000
0!
0$
0%
0)
0,
0-
b1010 9
#205000
1!
b1000 &
1'
1)
b1000 .
1/
b11 1
b0 6
#210000
0!
0)
#215000
1!
b11000000100010010101111010000001 &
1)
b11000000100010010101111010000001 .
b1 6
#220000
0!
b111011001000111111000101110110 #
1$
0)
b111011001000111111000101110110 +
1,
b0 9
#225000
1!
b10000100100001001101011000001001 &
1)
b10000100100001001101011000001001 .
b10 6
#230000
0!
b11110100011011100110100111101 #
0)
b11110100011011100110100111101 +
b1 9
#235000
1!
b10110001111100000101011001100011 &
1)
b10110001111100000101011001100011 .
b11 6
#240000
0!
b1110110110101000101011111101101 #
0)
b1110110110101000101011111101101 +
b10 9
#245000
1!
b110101110010111101100001101 &
1)
b110101110010111101100001101 .
b100 6
#250000
0!
b1000110001011011111011110001100 #
0)
b1000110001011011111011110001100 +
b11 9
#255000
1!
b1000110110111111001100110001101 &
1)
b1000110110111111001100110001101 .
b101 6
#260000
0!
b1111100111111011110100111111001 #
0)
b1111100111111011110100111111001 +
b100 9
#265000
1!
b10110010110000101000010001100101 &
1)
b10110010110000101000010001100101 .
b110 6
#270000
0!
b11100011001101110010010011000110 #
0)
b11100011001101110010010011000110 +
b101 9
#275000
1!
b10001001001101110101001000010010 &
1)
b10001001001101110101001000010010 .
b111 6
#280000
0!
b11100010111101111000010011000101 #
0)
b11100010111101111000010011000101 +
b110 9
#285000
1!
b111100111110001100000001 &
1)
b111100111110001100000001 .
b1000 6
#290000
0!
b11010101000100111101001010101010 #
0)
b11010101000100111101001010101010 +
b111 9
#295000
1!
b110110101111100110100001101 &
1)
b110110101111100110100001101 .
b0 1
#300000
0!
b1110010101011111111011111100101 #
0)
b1110010101011111111011111100101 +
b1000 9
#305000
1!
0'
1)
0/
b1 1
b0 4
#310000
0!
b10111011110100100111001001110111 #
1%
0)
b10111011110100100111001001110111 +
1-
b1001 9
#315000
1!
1)
b10 1
b10 3
b1 4
b10000000000000000 5
#320000
0!
0$
0%
0)
0,
0-
b1010 9
#325000
1!
b10000000000000000 &
1'
1)
b10000000000000000 .
1/
b11 1
b0 6
#330000
0!
0)
#335000
1!
b10111011110100100111001001110111 &
1)
b10111011110100100111001001110111 .
b0 1
#340000
0!
b10001001001100101101011000010010 #
1$
0)
b10001001001100101101011000010010 +
1,
b101111101 8
b0 9
#345000
1!
0'
1)
0/
b1 1
b0 4
#350000
0!
b1000111111011001101101110001111 #
0)
b1000111111011001101101110001111 +
b1 9
#355000
1!
1)
b1 4
#360000
0!
b1111001001100000110100111110010 #
0)
b1111001001100000110100111110010 +
b10 9
#365000
1!
1)
b10 4
#370000
0!
b11100111011101101001011011001110 #
0)
b11100111011101101001011011001110 +
b11 9
#375000
1!
1)
b11 4
#380000
0!
b11110100000000000111101011101000 #
0)
b11110100000000000111101011101000 +
b100 9
#385000
1!
1)
b100 4
#390000
0!
b11100010110010100100111011000101 #
0)
b11100010110010100100111011000101 +
b101 9
#395000
1!
1)
b101 4
#400000
0!
b101110010110000100100101011100 #
0)
b101110010110000100100101011100 +
b110 9
#405000
1!
1)
b110 4
#410000
0!
b11011110100011100010100010111101 #
0)
b11011110100011100010100010111101 +
b111 9
#415000
1!
1)
b111 4
#420000
0!
b10010110101010110101100000101101 #
0)
b10010110101010110101100000101101 +
b1000 9
#425000
1!
1)
b1000 4
#430000
0!
b10110010101001110010011001100101 #
0)
b10110010101001110010011001100101 +
b1001 9
#435000
1!
1)
b1001 4
#440000
0!
b10110001111011110110001001100011 #
0)
b10110001111011110110001001100011 +
b1010 9
#445000
1!
1)
b1010 4
#450000
0!
b101011100111000011100001010 #
0)
b101011100111000011100001010 +
b1011 9
#455000
1!
1)
b1011 4
#460000
0!
b11000000001110110010001010000000 #
0)
b11000000001110110010001010000000 +
b1100 9
#465000
1!
1)
b1100 4
#470000
0!
b10000011001000010000100100000 #
0)
b10000011001000010000100100000 +
b1101 9
#475000
1!
1)
b1101 4
#480000
0!
b1010101011110000100010110101010 #
0)
b1010101011110000100010110101010 +
b1110 9
#485000
1!
1)
b1110 4
#490000
0!
b11001110110011001100110010011101 #
0)
b11001110110011001100110010011101 +
b1111 9
#495000
1!
1)
b1111 4
#500000
0!
b11001011001000000011111010010110 #
0)
b11001011001000000011111010010110 +
b10000 9
#505000
1!
1)
b10000 4
#510000
0!
b10001001100000111011100000010011 #
0)
b10001001100000111011100000010011 +
b10001 9
#515000
1!
1)
b10001 4
#520000
0!
b10000110101111000011100000001101 #
0)
b10000110101111000011100000001101 +
b10010 9
#525000
1!
1)
b10010 4
#530000
0!
b10101001101001111101011001010011 #
0)
b10101001101001111101011001010011 +
b10011 9
#535000
1!
1)
b10011 4
#540000
0!
b110101100111111101110101101011 #
0)
b110101100111111101110101101011 +
b10100 9
#545000
1!
1)
b10100 4
#550000
0!
b11101010101001100010101011010101 #
0)
b11101010101001100010101011010101 +
b10101 9
#555000
1!
1)
b10101 4
#560000
0!
b10000001000101110100101000000010 #
0)
b10000001000101110100101000000010 +
b10110 9
#565000
1!
1)
b10110 4
#570000
0!
b11010111010101100011111010101110 #
0)
b11010111010101100011111010101110 +
b10111 9
#575000
1!
1)
b10111 4
#580000
0!
b1110111111111110100100011101 #
0)
b1110111111111110100100011101 +
b11000 9
#585000
1!
1)
b11000 4
#590000
0!
b11100111110001010111001011001111 #
0)
b11100111110001010111001011001111 +
b11001 9
#595000
1!
1)
b11001 4
#600000
0!
b10001100001000100100100100011 #
0)
b10001100001000100100100100011 +
b11010 9
#605000
1!
1)
b11010 4
#610000
0!
b101000010010110010100001010 #
0)
b101000010010110010100001010 +
b11011 9
#615000
1!
1)
b11011 4
#620000
0!
b11100101011100110000101011001010 #
0)
b11100101011100110000101011001010 +
b11100 9
#625000
1!
1)
b11100 4
#630000
0!
b10011110001100010100110000111100 #
0)
b10011110001100010100110000111100 +
b11101 9
#635000
1!
1)
b11101 4
#640000
0!
b1111001011010001011110111110010 #
0)
b1111001011010001011110111110010 +
b11110 9
#645000
1!
1)
b11110 4
#650000
0!
b1000101001011100110000110001010 #
0)
b1000101001011100110000110001010 +
b11111 9
#655000
1!
1)
b11111 4
#660000
0!
b100000110001001011001101000001 #
0)
b100000110001001011001101000001 +
b100000 9
#665000
1!
1)
b100000 4
#670000
0!
b11101100010010110011010011011000 #
0)
b11101100010010110011010011011000 +
b100001 9
#675000
1!
1)
b100001 4
#680000
0!
b111100001000001111001101111000 #
0)
b111100001000001111001101111000 +
b100010 9
#685000
1!
1)
b100010 4
#690000
0!
b11000100100010100001001010001001 #
0)
b11000100100010100001001010001001 +
b100011 9
#695000
1!
1)
b100011 4
#700000
0!
b1110101110001010000110111101011 #
0)
b1110101110001010000110111101011 +
b100100 9
#705000
1!
1)
b100100 4
#710000
0!
b1011011000000100110010110110110 #
0)
b1011011000000100110010110110110 +
b100101 9
#715000
1!
1)
b100101 4
#720000
0!
b1100011010010111111100111000110 #
0)
b1100011010010111111100111000110 +
b100110 9
#725000
1!
1)
b100110 4
#730000
0!
b1010111000101010001001110101110 #
0)
b1010111000101010001001110101110 +
b100111 9
#735000
1!
1)
b100111 4
#740000
0!
b11011110011101010000001010111100 #
0)
b11011110011101010000001010111100 +
b101000 9
#745000
1!
1)
b101000 4
#750000
0!
b10101000011111101110100101010 #
0)
b10101000011111101110100101010 +
b101001 9
#755000
1!
1)
b101001 4
#760000
0!
b10000101110101111001101000001011 #
0)
b10000101110101111001101000001011 +
b101010 9
#765000
1!
1)
b101010 4
#770000
0!
b10111000100101111011111001110001 #
0)
b10111000100101111011111001110001 +
b101011 9
#775000
1!
1)
b101011 4
#780000
0!
b1000010111100100100000110000101 #
0)
b1000010111100100100000110000101 +
b101100 9
#785000
1!
1)
b101100 4
#790000
0!
b100111111100100101010101001111 #
0)
b100111111100100101010101001111 +
b101101 9
#795000
1!
1)
b101101 4
#800000
0!
b10011101110011000110000000111011 #
0)
b10011101110011000110000000111011 +
b101110 9
#805000
1!
1)
b101110 4
#810000
0!
b11101000001100011001100111010 #
0)
b11101000001100011001100111010 +
b101111 9
#815000
1!
1)
b101111 4
#820000
0!
b10111111001000110011001001111110 #
0)
b10111111001000110011001001111110 +
b110000 9
#825000
1!
1)
b110000 4
#830000
0!
b1010101010100100101100010101 #
0)
b1010101010100100101100010101 +
b110001 9
#835000
1!
1)
b110001 4
#840000
0!
b1111000110110011001101111110001 #
0)
b1111000110110011001101111110001 +
b110010 9
#845000
1!
1)
b110010 4
#850000
0!
b1101100100111000100101111011001 #
0)
b1101100100111000100101111011001 +
b110011 9
#855000
1!
1)
b110011 4
#860000
0!
b110001001000110000011101100010 #
0)
b110001001000110000011101100010 +
b110100 9
#865000
1!
1)
b110100 4
#870000
0!
b100110001101011111101101001100 #
0)
b100110001101011111101101001100 +
b110101 9
#875000
1!
1)
b110101 4
#880000
0!
b1001111101000010101010110011111 #
0)
b1001111101000010101010110011111 +
b110110 9
#885000
1!
1)
b110110 4
#890000
0!
b1000111101110011010000110001111 #
0)
b1000111101110011010000110001111 +
b110111 9
#895000
1!
1)
b110111 4
#900000
0!
b1111100011011011010100111111000 #
0)
b1111100011011011010100111111000 +
b111000 9
#905000
1!
1)
b111000 4
#910000
0!
b11011011110011010110000010110111 #
0)
b11011011110011010110000010110111 +
b111001 9
#915000
1!
1)
b111001 4
#920000
0!
b11001111110001000101011010011111 #
0)
b11001111110001000101011010011111 +
b111010 9
#925000
1!
1)
b111010 4
#930000
0!
b10101110011111011001010001011100 #
0)
b10101110011111011001010001011100 +
b111011 9
#935000
1!
1)
b111011 4
#940000
0!
b10101101110010111100000001011011 #
0)
b10101101110010111100000001011011 +
b111100 9
#945000
1!
1)
b111100 4
#950000
0!
b1000100110111100011011110001001 #
0)
b1000100110111100011011110001001 +
b111101 9
#955000
1!
1)
b111101 4
#960000
0!
b10100100101011100011001001001001 #
0)
b10100100101011100011001001001001 +
b111110 9
#965000
1!
1)
b111110 4
#970000
0!
b11101000001000110011111011010000 #
0)
b11101000001000110011111011010000 +
b111111 9
#975000
1!
1)
b111111 4
#980000
0!
b11101011111111101100000011010111 #
0)
b11101011111111101100000011010111 +
b1000000 9
#985000
1!
1)
b1000000 4
#990000
0!
b10101000110001111111110001010001 #
0)
b10101000110001111111110001010001 +
b1000001 9
#995000
1!
1)
b1000001 4
#1000000
0!
b1001011001000010010111110010110 #
0)
b1001011001000010010111110010110 +
b1000010 9
